mater_data_providing/__init__.py
mater_data_providing/constants.py
mater_data_providing/definitions.py
mater_data_providing/file_operations.py
mater_data_providing/helpers.py
mater_data_providing/py.typed
mater_data_providing/serialization.py
mater_data_providing/transformations.py
mater_data_providing/validations.py
mater_data_providing-0.3.1.dist-info/METADATA
mater_data_providing-0.3.1.dist-info/WHEEL
mater_data_providing-0.3.1.dist-info/licenses/LICENSE
mater_data_providing-0.3.1.dist-info/RECORD
