Metadata-Version: 2.4
Name: mater-data-providing
Version: 0.3.1
Summary: Gives functions to help build a mater providing data script.
Author-email: francois-verzier <francois.verzier@univ-grenoble-alpes.fr>
License:                    GNU LESSER GENERAL PUBLIC LICENSE
License-File: LICENSE
Requires-Python: >=3.12
Requires-Dist: email-validator>=2.2.0
Requires-Dist: pandas>=2.2.3
